lightgbmmodeloptimizer/__init__.py
lightgbmmodeloptimizer/_tree.py
lightgbmmodeloptimizer/optimizer.py
lightgbmmodeloptimizer/utils.py
lightgbmmodeloptimizer-0.0.7.dist-info/METADATA
lightgbmmodeloptimizer-0.0.7.dist-info/WHEEL
lightgbmmodeloptimizer-0.0.7.dist-info/top_level.txt
lightgbmmodeloptimizer-0.0.7.dist-info/RECORD
