Metadata-Version: 2.4
Name: LightGBMModelOptimizer
Version: 0.0.7
Summary: Trained Lightgbm Model Optimizer. Reduce size and improve inference time of the trained lightgbm model
Author-email: Rajat Goyal <rajatgoyal376@gmail.com>
Maintainer-email: Paras Malik <paras.mal@media.net>
License: MIT
Classifier: Programming Language :: Python :: 3
Classifier: License :: OSI Approved :: MIT License
Classifier: Operating System :: OS Independent
Requires-Python: >=3.6
